[{"spec":0,"prob":0},{"spec":0.114,"prob":0.01},{"spec":0.285,"prob":0.02},{"spec":0.454,"prob":0.03},{"spec":0.585,"prob":0.04},{"spec":0.681,"prob":0.05},{"spec":0.767,"prob":0.06},{"spec":0.826,"prob":0.07},{"spec":0.874,"prob":0.08},{"spec":0.906,"prob":0.09},{"spec":0.935,"prob":0.1},{"spec":0.955,"prob":0.11},{"spec":0.966,"prob":0.12},{"spec":0.973,"prob":0.13},{"spec":0.983,"prob":0.14},{"spec":0.989,"prob":0.15},{"spec":0.996,"prob":0.16},{"spec":0.998,"prob":0.17},{"spec":0.998,"prob":0.18},{"spec":0.999,"prob":0.19},{"spec":0.999,"prob":0.2},{"spec":0.999,"prob":0.21},{"spec":0.999,"prob":0.22},{"spec":0.999,"prob":0.23},{"spec":1,"prob":0.24},{"spec":1,"prob":0.25},{"spec":1,"prob":0.26},{"spec":1,"prob":0.27},{"spec":1,"prob":0.28},{"spec":1,"prob":0.29},{"spec":1,"prob":0.3},{"spec":1,"prob":0.31},{"spec":1,"prob":0.32},{"spec":1,"prob":0.33},{"spec":1,"prob":0.34},{"spec":1,"prob":0.35},{"spec":1,"prob":0.36},{"spec":1,"prob":0.37},{"spec":1,"prob":0.38},{"spec":1,"prob":0.39},{"spec":1,"prob":0.4},{"spec":1,"prob":0.41},{"spec":1,"prob":0.42},{"spec":1,"prob":0.43},{"spec":1,"prob":0.44},{"spec":1,"prob":0.45},{"spec":1,"prob":0.46},{"spec":1,"prob":0.47},{"spec":1,"prob":0.48},{"spec":1,"prob":0.49},{"spec":1,"prob":0.5},{"spec":1,"prob":0.51},{"spec":1,"prob":0.52},{"spec":1,"prob":0.53},{"spec":1,"prob":0.54},{"spec":1,"prob":0.55},{"spec":1,"prob":0.56},{"spec":1,"prob":0.57},{"spec":1,"prob":0.58},{"spec":1,"prob":0.59},{"spec":1,"prob":0.6},{"spec":1,"prob":0.61},{"spec":1,"prob":0.62},{"spec":1,"prob":0.63},{"spec":1,"prob":0.64},{"spec":1,"prob":0.65},{"spec":1,"prob":0.66},{"spec":1,"prob":0.67},{"spec":1,"prob":0.68},{"spec":1,"prob":0.69},{"spec":1,"prob":0.7},{"spec":1,"prob":0.71},{"spec":1,"prob":0.72},{"spec":1,"prob":0.73},{"spec":1,"prob":0.74},{"spec":1,"prob":0.75},{"spec":1,"prob":0.76},{"spec":1,"prob":0.77},{"spec":1,"prob":0.78},{"spec":1,"prob":0.79},{"spec":1,"prob":0.8},{"spec":1,"prob":0.81},{"spec":1,"prob":0.82},{"spec":1,"prob":0.83},{"spec":1,"prob":0.84},{"spec":1,"prob":0.85},{"spec":1,"prob":0.86},{"spec":1,"prob":0.87},{"spec":1,"prob":0.88},{"spec":1,"prob":0.89},{"spec":1,"prob":0.9},{"spec":1,"prob":0.91},{"spec":1,"prob":0.92},{"spec":1,"prob":0.93},{"spec":1,"prob":0.94},{"spec":1,"prob":0.95},{"spec":1,"prob":0.96},{"spec":1,"prob":0.97},{"spec":1,"prob":0.98},{"spec":1,"prob":0.99},{"spec":1,"prob":1}]
